setup.py
TicTacToe_python_game/__init__.py
TicTacToe_python_game/main.py
TicTacToe_python_game/tic_tac_toe.py
TicTacToe_python_game.egg-info/PKG-INFO
TicTacToe_python_game.egg-info/SOURCES.txt
TicTacToe_python_game.egg-info/dependency_links.txt
TicTacToe_python_game.egg-info/not-zip-safe
TicTacToe_python_game.egg-info/top_level.txt