Metadata-Version: 1.0
Name: TicTacToe-python-game
Version: 0.1
Summary: Tictactoe Game
Home-page: UNKNOWN
Author: Aman Kumbhani
Author-email: amankumbhani@gmail.com
License: UNKNOWN
Platform: UNKNOWN
